[
  {
    "author": {},
    "attrs": {
      "language": "pt"
    },
    "type": "Question",
    "text_formatted": "Gostaria de saber como preparar a criança com nanismo para o mundo escolar e os preconceitos possíveis à acontecer ?",
    "event_question_id": 25791921,
    "event_id": 2815079,
    "event_section_id": 3195394,
    "text": "Gostaria de saber como preparar a criança com nanismo para o mundo escolar e os preconceitos possíveis à acontecer ?",
    "is_public": true,
    "is_answered": false,
    "is_highlighted": false,
    "is_anonymous": true,
    "is_bookmarked": false,
    "score": 12,
    "score_positive": 12,
    "score_negative": 0,
    "date_published": null,
    "date_highlighted": null,
    "path": "/questions",
    "date_created": "2020-10-20T04:01:29.000Z",
    "date_updated": "2020-10-20T04:01:29.000Z",
    "date_deleted": null,
    "labels": [],
    "pinned_replies": []
  },
  {
    "author": {},
    "attrs": {
      "language": "pt"
    },
    "type": "Question",
    "text_formatted": "Como os pais podem criar seus filhos com nanismo com a força necessária para enfrentar (e superar) os desafios da vida?",
    "event_question_id": 25725482,
    "event_id": 2815079,
    "event_section_id": 3195394,
    "text": "Como os pais podem criar seus filhos com nanismo com a força necessária para enfrentar (e superar) os desafios da vida?",
    "is_public": true,
    "is_answered": false,
    "is_highlighted": false,
    "is_anonymous": true,
    "is_bookmarked": false,
    "score": 11,
    "score_positive": 11,
    "score_negative": 0,
    "date_published": null,
    "date_highlighted": null,
    "path": "/questions",
    "date_created": "2020-10-18T20:05:48.000Z",
    "date_updated": "2020-10-18T20:05:48.000Z",
    "date_deleted": null,
    "labels": [],
    "pinned_replies": []
  },
  {
    "author": {},
    "attrs": {
      "language": "pt"
    },
    "type": "Question",
    "text_formatted": "Dra. Qual a melhor forma de falar sobre as diferenças com os nossos filhos? ",
    "event_question_id": 26228254,
    "event_id": 2815079,
    "event_section_id": 3195394,
    "text": "Dra. Qual a melhor forma de falar sobre as diferenças com os nossos filhos? ",
    "is_public": true,
    "is_answered": false,
    "is_highlighted": false,
    "is_anonymous": true,
    "is_bookmarked": false,
    "score": 9,
    "score_positive": 9,
    "score_negative": 0,
    "date_published": null,
    "date_highlighted": null,
    "path": "/questions",
    "date_created": "2020-10-27T17:05:32.000Z",
    "date_updated": "2020-10-27T17:05:32.000Z",
    "date_deleted": null,
    "labels": [],
    "pinned_replies": []
  },
  {
    "author": {},
    "attrs": {
      "language": "pt"
    },
    "type": "Question",
    "text_formatted": "Até que idade se define a personalidade de uma criança e de que forma podemos ajudar os nossos filhos a ter uma personalidade com auto estima e coragem?",
    "event_question_id": 26275584,
    "event_id": 2815079,
    "event_section_id": 3195394,
    "text": "Até que idade se define a personalidade de uma criança e de que forma podemos ajudar os nossos filhos a ter uma personalidade com auto estima e coragem?",
    "is_public": true,
    "is_answered": false,
    "is_highlighted": false,
    "is_anonymous": true,
    "is_bookmarked": false,
    "score": 9,
    "score_positive": 9,
    "score_negative": 0,
    "date_published": null,
    "date_highlighted": null,
    "path": "/questions",
    "date_created": "2020-10-28T11:43:06.000Z",
    "date_updated": "2020-10-28T11:43:06.000Z",
    "date_deleted": null,
    "labels": [],
    "pinned_replies": []
  },
  {
    "author": {},
    "attrs": {
      "language": "pt"
    },
    "type": "Question",
    "text_formatted": "Dra. Como trabalhar a autonomia da criança?",
    "event_question_id": 26227971,
    "event_id": 2815079,
    "event_section_id": 3195394,
    "text": "Dra. Como trabalhar a autonomia da criança?",
    "is_public": true,
    "is_answered": false,
    "is_highlighted": false,
    "is_anonymous": true,
    "is_bookmarked": false,
    "score": 8,
    "score_positive": 8,
    "score_negative": 0,
    "date_published": null,
    "date_highlighted": null,
    "path": "/questions",
    "date_created": "2020-10-27T17:01:32.000Z",
    "date_updated": "2020-10-27T17:01:32.000Z",
    "date_deleted": null,
    "labels": [],
    "pinned_replies": []
  },
  {
    "author": {},
    "attrs": {
      "language": "pt"
    },
    "type": "Question",
    "text_formatted": "Qual idade as crianças começam a perceber as diferenças entre elas e como fazer essa primeira abordagem?",
    "event_question_id": 26275755,
    "event_id": 2815079,
    "event_section_id": 3195394,
    "text": "Qual idade as crianças começam a perceber as diferenças entre elas e como fazer essa primeira abordagem?",
    "is_public": true,
    "is_answered": false,
    "is_highlighted": false,
    "is_anonymous": true,
    "is_bookmarked": false,
    "score": 7,
    "score_positive": 7,
    "score_negative": 0,
    "date_published": null,
    "date_highlighted": null,
    "path": "/questions",
    "date_created": "2020-10-28T11:45:46.000Z",
    "date_updated": "2020-10-28T11:45:46.000Z",
    "date_deleted": null,
    "labels": [],
    "pinned_replies": []
  },
  {
    "author": {},
    "attrs": {
      "language": "pt"
    },
    "type": "Question",
    "text_formatted": "Como reagir quando alguém tira foto minha? Sempre me dá vontade de apontar o dedo ",
    "event_question_id": 26060777,
    "event_id": 2815079,
    "event_section_id": 3195394,
    "text": "Como reagir quando alguém tira foto minha? Sempre me dá vontade de apontar o dedo ",
    "is_public": true,
    "is_answered": false,
    "is_highlighted": false,
    "is_anonymous": true,
    "is_bookmarked": false,
    "score": 6,
    "score_positive": 6,
    "score_negative": 0,
    "date_published": null,
    "date_highlighted": null,
    "path": "/questions",
    "date_created": "2020-10-23T12:46:17.000Z",
    "date_updated": "2020-10-23T12:46:17.000Z",
    "date_deleted": null,
    "labels": [],
    "pinned_replies": []
  },
  {
    "author": {},
    "attrs": {
      "language": "pt"
    },
    "type": "Question",
    "text_formatted": "Tenho 3 filhos e o mais novo  tem acondroplasia. Como lidar com os outros filhos de forma não causar ciúmes entre eles?",
    "event_question_id": 26156558,
    "event_id": 2815079,
    "event_section_id": 3195394,
    "text": "Tenho 3 filhos e o mais novo  tem acondroplasia. Como lidar com os outros filhos de forma não causar ciúmes entre eles?",
    "is_public": true,
    "is_answered": false,
    "is_highlighted": false,
    "is_anonymous": true,
    "is_bookmarked": false,
    "score": 6,
    "score_positive": 6,
    "score_negative": 0,
    "date_published": null,
    "date_highlighted": null,
    "path": "/questions",
    "date_created": "2020-10-26T14:43:43.000Z",
    "date_updated": "2020-10-26T14:43:43.000Z",
    "date_deleted": null,
    "labels": [],
    "pinned_replies": []
  },
  {
    "author": {},
    "attrs": {
      "language": "pt"
    },
    "type": "Question",
    "text_formatted": "Olá, Dra.! Como lidar e contornar as inseguranças do filho absorvidas dos pais?",
    "event_question_id": 26227814,
    "event_id": 2815079,
    "event_section_id": 3195394,
    "text": "Olá, Dra.! Como lidar e contornar as inseguranças do filho absorvidas dos pais?",
    "is_public": true,
    "is_answered": false,
    "is_highlighted": false,
    "is_anonymous": true,
    "is_bookmarked": false,
    "score": 6,
    "score_positive": 6,
    "score_negative": 0,
    "date_published": null,
    "date_highlighted": null,
    "path": "/questions",
    "date_created": "2020-10-27T16:59:22.000Z",
    "date_updated": "2020-10-27T16:59:22.000Z",
    "date_deleted": null,
    "labels": [],
    "pinned_replies": []
  },
  {
    "author": {},
    "attrs": {
      "language": "pt"
    },
    "type": "Question",
    "text_formatted": "Dra. Qual sua visão sobre a forma como chamar o nanismo? aqui é como falamos, e anão é o que minha filha conhece nos desenhos, sabe que é pequena pq tem nanismo",
    "event_question_id": 26329525,
    "event_id": 2815079,
    "event_section_id": 3195394,
    "text": "Dra. Qual sua visão sobre a forma como chamar o nanismo? aqui é como falamos, e anão é o que minha filha conhece nos desenhos, sabe que é pequena pq tem nanismo",
    "is_public": true,
    "is_answered": false,
    "is_highlighted": false,
    "is_anonymous": true,
    "is_bookmarked": false,
    "score": 6,
    "score_positive": 6,
    "score_negative": 0,
    "date_published": null,
    "date_highlighted": null,
    "path": "/questions",
    "date_created": "2020-10-29T03:50:49.000Z",
    "date_updated": "2020-10-29T03:50:49.000Z",
    "date_deleted": null,
    "labels": [],
    "pinned_replies": []
  },
  {
    "author": {},
    "attrs": {
      "language": "pt"
    },
    "type": "Question",
    "text_formatted": "Dra. Como reverter na criança a absorção do processo de ansiedade, da preocupação com o futuro que de alguma forma os pais passaram para ela?",
    "event_question_id": 26228162,
    "event_id": 2815079,
    "event_section_id": 3195394,
    "text": "Dra. Como reverter na criança a absorção do processo de ansiedade, da preocupação com o futuro que de alguma forma os pais passaram para ela?",
    "is_public": true,
    "is_answered": false,
    "is_highlighted": false,
    "is_anonymous": true,
    "is_bookmarked": false,
    "score": 5,
    "score_positive": 5,
    "score_negative": 0,
    "date_published": null,
    "date_highlighted": null,
    "path": "/questions",
    "date_created": "2020-10-27T17:04:03.000Z",
    "date_updated": "2020-10-27T17:04:03.000Z",
    "date_deleted": null,
    "labels": [],
    "pinned_replies": []
  },
  {
    "author": {},
    "attrs": {
      "language": "pt"
    },
    "type": "Question",
    "text_formatted": "Doutora Mirella gostaria de saber um pouco sobre o que seria luto do diagnóstico?",
    "event_question_id": 26180348,
    "event_id": 2815079,
    "event_section_id": 3195394,
    "text": "Doutora Mirella gostaria de saber um pouco sobre o que seria luto do diagnóstico?",
    "is_public": true,
    "is_answered": false,
    "is_highlighted": false,
    "is_anonymous": true,
    "is_bookmarked": false,
    "score": 4,
    "score_positive": 4,
    "score_negative": 0,
    "date_published": null,
    "date_highlighted": null,
    "path": "/questions",
    "date_created": "2020-10-27T01:51:44.000Z",
    "date_updated": "2020-10-27T01:51:44.000Z",
    "date_deleted": null,
    "labels": [],
    "pinned_replies": []
  },
  {
    "author": {},
    "attrs": {
      "language": "pt"
    },
    "type": "Question",
    "text_formatted": "Dra. Qual a melhor maneira de encarar o preconceito?",
    "event_question_id": 26228377,
    "event_id": 2815079,
    "event_section_id": 3195394,
    "text": "Dra. Qual a melhor maneira de encarar o preconceito?",
    "is_public": true,
    "is_answered": false,
    "is_highlighted": false,
    "is_anonymous": true,
    "is_bookmarked": false,
    "score": 4,
    "score_positive": 4,
    "score_negative": 0,
    "date_published": null,
    "date_highlighted": null,
    "path": "/questions",
    "date_created": "2020-10-27T17:07:11.000Z",
    "date_updated": "2020-10-27T17:07:11.000Z",
    "date_deleted": null,
    "labels": [],
    "pinned_replies": []
  },
  {
    "author": {},
    "attrs": {
      "language": "pt"
    },
    "type": "Question",
    "text_formatted": "Gostaria que você abordasse novamente sobre a culpa existente nos pais e nos outros filhos que não possuem nenhuma condição especial.",
    "event_question_id": 26253283,
    "event_id": 2815079,
    "event_section_id": 3195394,
    "text": "Gostaria que você abordasse novamente sobre a culpa existente nos pais e nos outros filhos que não possuem nenhuma condição especial.",
    "is_public": true,
    "is_answered": false,
    "is_highlighted": false,
    "is_anonymous": true,
    "is_bookmarked": false,
    "score": 4,
    "score_positive": 4,
    "score_negative": 0,
    "date_published": null,
    "date_highlighted": null,
    "path": "/questions",
    "date_created": "2020-10-28T02:22:07.000Z",
    "date_updated": "2020-10-28T02:22:07.000Z",
    "date_deleted": null,
    "labels": [],
    "pinned_replies": []
  },
  {
    "author": {},
    "attrs": {
      "language": "pt"
    },
    "type": "Question",
    "text_formatted": "Como vencer a insegurança de ter outros filhos? Não pelo medo da deficiência, mas pelo sentimento do filho que tem alguma condição, como conduzir isso?",
    "event_question_id": 26329592,
    "event_id": 2815079,
    "event_section_id": 3195394,
    "text": "Como vencer a insegurança de ter outros filhos? Não pelo medo da deficiência, mas pelo sentimento do filho que tem alguma condição, como conduzir isso?",
    "is_public": true,
    "is_answered": false,
    "is_highlighted": false,
    "is_anonymous": true,
    "is_bookmarked": false,
    "score": 4,
    "score_positive": 4,
    "score_negative": 0,
    "date_published": null,
    "date_highlighted": null,
    "path": "/questions",
    "date_created": "2020-10-29T03:54:25.000Z",
    "date_updated": "2020-10-29T03:54:25.000Z",
    "date_deleted": null,
    "labels": [],
    "pinned_replies": []
  },
  {
    "author": {
      "attrs": {},
      "event_user_id": 114606654,
      "name": "Ana"
    },
    "attrs": {
      "language": "pt",
      "author_name": null
    },
    "type": "Question",
    "text_formatted": "Mirella, temos como apagar da memoria a percepção da recusa que nosso Cauê sentiu quando nasceu?? Eu senti isso por algumas horas e meu marido também. ",
    "event_question_id": 26223380,
    "event_id": 2815079,
    "event_section_id": 3195394,
    "event_user_id": 114606654,
    "text": "Mirella, temos como apagar da memoria a percepção da recusa que nosso Cauê sentiu quando nasceu?? Eu senti isso por algumas horas e meu marido também. ",
    "is_public": true,
    "is_answered": false,
    "is_highlighted": false,
    "is_anonymous": false,
    "is_bookmarked": false,
    "score": 3,
    "score_positive": 3,
    "score_negative": 0,
    "date_published": null,
    "date_highlighted": null,
    "path": "/questions",
    "date_created": "2020-10-27T16:01:59.000Z",
    "date_updated": "2020-10-27T16:01:59.000Z",
    "date_deleted": null,
    "labels": [],
    "pinned_replies": []
  },
  {
    "author": {},
    "attrs": {
      "language": "pt"
    },
    "type": "Question",
    "text_formatted": "O que fazer quando alguém nos olha demais ou mostra para outras pessoas?",
    "event_question_id": 26449129,
    "event_id": 2815079,
    "event_section_id": 3195394,
    "text": "O que fazer quando alguém nos olha demais ou mostra para outras pessoas?",
    "is_public": true,
    "is_answered": false,
    "is_highlighted": false,
    "is_anonymous": true,
    "is_bookmarked": false,
    "score": 3,
    "score_positive": 3,
    "score_negative": 0,
    "date_published": null,
    "date_highlighted": null,
    "path": "/questions",
    "date_created": "2020-10-30T23:35:28.000Z",
    "date_updated": "2020-10-30T23:35:28.000Z",
    "date_deleted": null,
    "labels": [],
    "pinned_replies": []
  },
  {
    "author": {},
    "attrs": {
      "language": "pt"
    },
    "type": "Question",
    "text_formatted": "Ola. Tenho 35 anos e sou portadora de nanismo pituitária. Nessa altura do campeonato, ainda há o que se fazer pra melhorar a estatura?",
    "event_question_id": 26030568,
    "event_id": 2815079,
    "event_section_id": 3195394,
    "text": "Ola. Tenho 35 anos e sou portadora de nanismo pituitária. Nessa altura do campeonato, ainda há o que se fazer pra melhorar a estatura?",
    "is_public": true,
    "is_answered": false,
    "is_highlighted": false,
    "is_anonymous": true,
    "is_bookmarked": false,
    "score": 2,
    "score_positive": 2,
    "score_negative": 0,
    "date_published": null,
    "date_highlighted": null,
    "path": "/questions",
    "date_created": "2020-10-23T00:22:37.000Z",
    "date_updated": "2020-10-23T00:22:37.000Z",
    "date_deleted": null,
    "labels": [],
    "pinned_replies": []
  },
  {
    "author": {},
    "attrs": {
      "language": "pt"
    },
    "type": "Question",
    "text_formatted": "Como posso ajudar meu filho a não sofrer com o preconceito? ",
    "event_question_id": 26033066,
    "event_id": 2815079,
    "event_section_id": 3195394,
    "text": "Como posso ajudar meu filho a não sofrer com o preconceito? ",
    "is_public": true,
    "is_answered": false,
    "is_highlighted": false,
    "is_anonymous": true,
    "is_bookmarked": false,
    "score": 2,
    "score_positive": 2,
    "score_negative": 0,
    "date_published": null,
    "date_highlighted": null,
    "path": "/questions",
    "date_created": "2020-10-23T01:38:45.000Z",
    "date_updated": "2020-10-23T01:38:45.000Z",
    "date_deleted": null,
    "labels": [],
    "pinned_replies": []
  },
  {
    "author": {},
    "attrs": {
      "language": "pt"
    },
    "type": "Question",
    "text_formatted": "Assisti a sua última live com a Juliana. Como obter a cura?",
    "event_question_id": 26443531,
    "event_id": 2815079,
    "event_section_id": 3195394,
    "text": "Assisti a sua última live com a Juliana. Como obter a cura?",
    "is_public": true,
    "is_answered": false,
    "is_highlighted": false,
    "is_anonymous": true,
    "is_bookmarked": false,
    "score": 2,
    "score_positive": 2,
    "score_negative": 0,
    "date_published": null,
    "date_highlighted": null,
    "path": "/questions",
    "date_created": "2020-10-30T19:25:30.000Z",
    "date_updated": "2020-10-30T19:25:30.000Z",
    "date_deleted": null,
    "labels": [],
    "pinned_replies": []
  },
  {
    "author": {},
    "attrs": {
      "language": "pt"
    },
    "type": "Question",
    "text_formatted": "Já fico pensando quando minha filha for para a escola e ser rejeitada  de ser par de algum menino na festa junina. Se isso ocorrer, como lidar com isso?",
    "event_question_id": 26443611,
    "event_id": 2815079,
    "event_section_id": 3195394,
    "text": "Já fico pensando quando minha filha for para a escola e ser rejeitada  de ser par de algum menino na festa junina. Se isso ocorrer, como lidar com isso?",
    "is_public": true,
    "is_answered": false,
    "is_highlighted": false,
    "is_anonymous": true,
    "is_bookmarked": false,
    "score": 2,
    "score_positive": 2,
    "score_negative": 0,
    "date_published": null,
    "date_highlighted": null,
    "path": "/questions",
    "date_created": "2020-10-30T19:27:31.000Z",
    "date_updated": "2020-10-30T19:27:31.000Z",
    "date_deleted": null,
    "labels": [],
    "pinned_replies": []
  },
  {
    "author": {},
    "attrs": {
      "language": "pt"
    },
    "type": "Question",
    "text_formatted": "Mirella, tudo bem? Qual seria o melhor momento(idade) de contarmos sobre nanismo aos nossos filhos? Qual seria a forma mais sútil de abordar o assunto? ",
    "event_question_id": 26449030,
    "event_id": 2815079,
    "event_section_id": 3195394,
    "text": "Mirella, tudo bem? Qual seria o melhor momento(idade) de contarmos sobre nanismo aos nossos filhos? Qual seria a forma mais sútil de abordar o assunto? ",
    "is_public": true,
    "is_answered": false,
    "is_highlighted": false,
    "is_anonymous": true,
    "is_bookmarked": false,
    "score": 2,
    "score_positive": 2,
    "score_negative": 0,
    "date_published": null,
    "date_highlighted": null,
    "path": "/questions",
    "date_created": "2020-10-30T23:27:35.000Z",
    "date_updated": "2020-10-30T23:27:35.000Z",
    "date_deleted": null,
    "labels": [],
    "pinned_replies": []
  },
  {
    "author": {},
    "attrs": {
      "language": "pt"
    },
    "type": "Question",
    "text_formatted": "Existem vários tipos de acondroplasia? ",
    "event_question_id": 26449081,
    "event_id": 2815079,
    "event_section_id": 3195394,
    "text": "Existem vários tipos de acondroplasia? ",
    "is_public": true,
    "is_answered": false,
    "is_highlighted": false,
    "is_anonymous": true,
    "is_bookmarked": false,
    "score": 2,
    "score_positive": 2,
    "score_negative": 0,
    "date_published": null,
    "date_highlighted": null,
    "path": "/questions",
    "date_created": "2020-10-30T23:32:29.000Z",
    "date_updated": "2020-10-30T23:32:29.000Z",
    "date_deleted": null,
    "labels": [],
    "pinned_replies": []
  },
  {
    "author": {},
    "attrs": {
      "language": "pt"
    },
    "type": "Question",
    "text_formatted": "Com que idade pode começas o tratamento de acondroplasia com a nova medicação ?",
    "event_question_id": 26449094,
    "event_id": 2815079,
    "event_section_id": 3195394,
    "text": "Com que idade pode começas o tratamento de acondroplasia com a nova medicação ?",
    "is_public": true,
    "is_answered": false,
    "is_highlighted": false,
    "is_anonymous": true,
    "is_bookmarked": false,
    "score": 2,
    "score_positive": 2,
    "score_negative": 0,
    "date_published": null,
    "date_highlighted": null,
    "path": "/questions",
    "date_created": "2020-10-30T23:33:20.000Z",
    "date_updated": "2020-10-30T23:33:20.000Z",
    "date_deleted": null,
    "labels": [],
    "pinned_replies": []
  },
  {
    "author": {},
    "attrs": {
      "language": "pt"
    },
    "type": "Question",
    "text_formatted": "Olá! Sou pai de um gatão com DD de 01 ano e 10 meses. O que podemos fazer para amenizar a escoliose progressiva e o risco de possível compressão na medula?",
    "event_question_id": 26114412,
    "event_id": 2815079,
    "event_section_id": 3195394,
    "text": "Olá! Sou pai de um gatão com DD de 01 ano e 10 meses. O que podemos fazer para amenizar a escoliose progressiva e o risco de possível compressão na medula?",
    "is_public": true,
    "is_answered": false,
    "is_highlighted": false,
    "is_anonymous": true,
    "is_bookmarked": false,
    "score": 1,
    "score_positive": 1,
    "score_negative": 0,
    "date_published": null,
    "date_highlighted": null,
    "path": "/questions",
    "date_created": "2020-10-25T02:45:02.000Z",
    "date_updated": "2020-10-25T02:45:02.000Z",
    "date_deleted": null,
    "labels": [],
    "pinned_replies": []
  },
  {
    "author": {},
    "attrs": {
      "language": "pt"
    },
    "type": "Question",
    "text_formatted": "Doutor Wagner gostaria de saber sobre colágenopatia tipo II? Existe tratamento?",
    "event_question_id": 26180380,
    "event_id": 2815079,
    "event_section_id": 3195394,
    "text": "Doutor Wagner gostaria de saber sobre colágenopatia tipo II? Existe tratamento?",
    "is_public": true,
    "is_answered": false,
    "is_highlighted": false,
    "is_anonymous": true,
    "is_bookmarked": false,
    "score": 1,
    "score_positive": 1,
    "score_negative": 0,
    "date_published": null,
    "date_highlighted": null,
    "path": "/questions",
    "date_created": "2020-10-27T01:53:27.000Z",
    "date_updated": "2020-10-27T01:53:27.000Z",
    "date_deleted": null,
    "labels": [],
    "pinned_replies": []
  },
  {
    "author": {
      "attrs": {},
      "event_user_id": 115703355,
      "name": "Jose Welington "
    },
    "attrs": {
      "language": "pt",
      "author_name": null
    },
    "type": "Question",
    "text_formatted": "Pais abalados psicologicamente por ter um filho c nanismo. Como gerenciar,qnd uma das partes não assimilou a nova realidade se sente vítima da situação? ",
    "event_question_id": 26450472,
    "event_id": 2815079,
    "event_section_id": 3195394,
    "event_user_id": 115703355,
    "text": "Pais abalados psicologicamente por ter um filho c nanismo. Como gerenciar,qnd uma das partes não assimilou a nova realidade se sente vítima da situação? ",
    "is_public": true,
    "is_answered": false,
    "is_highlighted": false,
    "is_anonymous": false,
    "is_bookmarked": false,
    "score": 1,
    "score_positive": 1,
    "score_negative": 0,
    "date_published": null,
    "date_highlighted": null,
    "path": "/questions",
    "date_created": "2020-10-31T01:13:10.000Z",
    "date_updated": "2020-10-31T01:13:10.000Z",
    "date_deleted": null,
    "labels": [],
    "pinned_replies": []
  },
  {
    "author": {
      "attrs": {},
      "event_user_id": 115703355,
      "name": "Jose Welington "
    },
    "attrs": {
      "language": "pt",
      "author_name": "Jose Welington "
    },
    "type": "Question",
    "text_formatted": "E como.isso pode influenciar no desenvvimento da criança sem e com nanismo ?",
    "event_question_id": 26450475,
    "event_id": 2815079,
    "event_section_id": 3195394,
    "event_user_id": 115703355,
    "text": "E como.isso pode influenciar no desenvvimento da criança sem e com nanismo ?",
    "is_public": true,
    "is_answered": false,
    "is_highlighted": false,
    "is_anonymous": false,
    "is_bookmarked": false,
    "score": 1,
    "score_positive": 1,
    "score_negative": 0,
    "date_published": null,
    "date_highlighted": null,
    "path": "/questions",
    "date_created": "2020-10-31T01:13:27.000Z",
    "date_updated": "2020-10-31T01:13:27.000Z",
    "date_deleted": null,
    "labels": [],
    "pinned_replies": []
  },
  {
    "author": {},
    "attrs": {
      "language": "pt"
    },
    "type": "Question",
    "text_formatted": "A rejeição de um feto qdo descobri o diagnóstico pode ter ficado no inconsciente do bebê? De alguma forma poderá afetar sua vida no futuro?",
    "event_question_id": 26456640,
    "event_id": 2815079,
    "event_section_id": 3195394,
    "text": "A rejeição de um feto qdo descobri o diagnóstico pode ter ficado no inconsciente do bebê? De alguma forma poderá afetar sua vida no futuro?",
    "is_public": true,
    "is_answered": false,
    "is_highlighted": false,
    "is_anonymous": true,
    "is_bookmarked": false,
    "score": 1,
    "score_positive": 1,
    "score_negative": 0,
    "date_published": null,
    "date_highlighted": null,
    "path": "/questions",
    "date_created": "2020-10-31T04:51:35.000Z",
    "date_updated": "2020-10-31T04:51:35.000Z",
    "date_deleted": null,
    "labels": [],
    "pinned_replies": []
  },
  {
    "author": {},
    "attrs": {
      "language": "pt"
    },
    "type": "Question",
    "text_formatted": "Como lidar com o medo de engravidar, medo de ter outro filho com o destino especial. ",
    "event_question_id": 26473370,
    "event_id": 2815079,
    "event_section_id": 3195394,
    "text": "Como lidar com o medo de engravidar, medo de ter outro filho com o destino especial. ",
    "is_public": true,
    "is_answered": false,
    "is_highlighted": false,
    "is_anonymous": true,
    "is_bookmarked": false,
    "score": 0,
    "score_positive": 0,
    "score_negative": 0,
    "date_published": null,
    "date_highlighted": null,
    "path": "/questions",
    "date_created": "2020-10-31T18:10:17.000Z",
    "date_updated": "2020-10-31T18:10:17.000Z",
    "date_deleted": null,
    "labels": [],
    "pinned_replies": []
  }
]
